astropath/astar.pyi
astropath/astar.cpython-310-i386-linux-gnu.so
astropath/__init__.pyi
astropath-1.0.0a1.dist-info/METADATA
astropath-1.0.0a1.dist-info/RECORD
astropath-1.0.0a1.dist-info/top_level.txt
astropath-1.0.0a1.dist-info/WHEEL
