Metadata-Version: 2.1
Name: astropath
Version: 1.0.0a1
Summary: A bunch of * pathfinding algorithms written in C for that extra squeeze of speed.
Author-email: Matiiss <matiiss@matiiss.com>
Project-URL: Homepage, https://github.com/Matiiss/astropath
Project-URL: Issues, https://github.com/Matiiss/astropath/issues
Classifier: Programming Language :: Python :: 3
Classifier: License :: OSI Approved :: MIT License
Classifier: Operating System :: OS Independent
Requires-Python: >=3.8
